fsrapiclient-0.5.2.dist-info/METADATA
fsrapiclient-0.5.2.dist-info/WHEEL
fsrapiclient-0.5.2.dist-info/entry_points.txt
fsrapiclient-0.5.2.dist-info/licenses/LICENSE
fsrapiclient/__version__.py
fsrapiclient/api.py
fsrapiclient/constants.py
fsrapiclient/exceptions.py
fsrapiclient-0.5.2.dist-info/RECORD
