Metadata-Version: 2.1
Name: fsrapiclient
Version: 0.5.2
Summary: Lightweight Python client library for the UK Financial Services Register RESTful API
Keywords: financial conduct authority,financial data,financial regulation,financial services,financial services register,prudential regulation authority,regulated markets,restful api,uk
Author-Email: "S. R. Murthy" <s.murthy@tutanota.com>
Maintainer-Email: "S. R. Murthy" <s.murthy@tutanota.com>
License: Mozilla Public License Version 2.0
Classifier: Environment :: Console
Classifier: Programming Language :: Python :: 3
Classifier: Programming Language :: Python :: 3.8
Classifier: Programming Language :: Python :: 3.9
Classifier: Programming Language :: Python :: 3.10
Classifier: Programming Language :: Python :: 3.11
Classifier: Programming Language :: Python :: 3.12
Classifier: Programming Language :: Python :: 3.13
Classifier: Development Status :: 5 - Production/Stable
Classifier: Operating System :: POSIX :: Linux
Classifier: Operating System :: MacOS
Classifier: Operating System :: Microsoft :: Windows
Project-URL: Homepage, https://fsrapiclient.readthedocs.io/index.html
Project-URL: Documentation, https://fsrapiclient.readthedocs.io
Project-URL: Repository, https://github.com/sr-murthy/fsrapiclient
Requires-Python: >=3.10
Requires-Dist: requests
Provides-Extra: user
Requires-Dist: jupyter; extra == "user"
